rxntools/__init__.py
rxntools/draw.py
rxntools/reaction.py
rxntools/rxn_enumerator.py
rxntools/utils.py
rxntools_kit-0.1.0.dist-info/METADATA
rxntools_kit-0.1.0.dist-info/WHEEL
rxntools_kit-0.1.0.dist-info/licenses/LICENSE
rxntools_kit-0.1.0.dist-info/RECORD
