Metadata-Version: 2.4
Name: rxntools-kit
Version: 0.1.0
Summary: A package of custom rdkit-based operations for reaction cheminformatics
License-File: LICENSE
Author: yashchainani21
Author-email: yashchainani2026@u.northwestern.edu
Requires-Python: >=3.10,<3.11
Classifier: Programming Language :: Python :: 3
Classifier: Programming Language :: Python :: 3.10
Requires-Dist: matplotlib (>=3.10.0,<4.0.0)
Requires-Dist: mmpdb (>=2.1,<3.0)
Requires-Dist: mols2grid (>=2.0.0,<3.0.0)
Requires-Dist: notebook (>=7.3.2,<8.0.0)
Requires-Dist: numpy (>=2.2.0,<3.0.0)
Requires-Dist: pandas (>=2.2.3,<3.0.0)
Requires-Dist: py3dmol (>=2.4.2,<3.0.0)
Requires-Dist: pytest (>=8.3.4,<9.0.0)
Requires-Dist: rdkit (>=2024.3.6,<2025.0.0)
Requires-Dist: scikit-learn (>=1.6.0,<2.0.0)
Requires-Dist: scipy (>=1.14.1,<2.0.0)
Requires-Dist: seaborn (>=0.13.2,<0.14.0)
